odoo/addons/maintenance_plan_activity/README.rst
odoo/addons/maintenance_plan_activity/__init__.py
odoo/addons/maintenance_plan_activity/__manifest__.py
odoo/addons/maintenance_plan_activity/i18n/es.po
odoo/addons/maintenance_plan_activity/i18n/it.po
odoo/addons/maintenance_plan_activity/i18n/maintenance_plan_activity.pot
odoo/addons/maintenance_plan_activity/i18n/pt.po
odoo/addons/maintenance_plan_activity/models/__init__.py
odoo/addons/maintenance_plan_activity/models/maintenance.py
odoo/addons/maintenance_plan_activity/models/maintenance_planned_activity.py
odoo/addons/maintenance_plan_activity/readme/CONTRIBUTORS.rst
odoo/addons/maintenance_plan_activity/readme/DESCRIPTION.rst
odoo/addons/maintenance_plan_activity/security/ir.model.access.csv
odoo/addons/maintenance_plan_activity/static/description/icon.png
odoo/addons/maintenance_plan_activity/static/description/index.html
odoo/addons/maintenance_plan_activity/static/description/maintenance_plan_activity.png
odoo/addons/maintenance_plan_activity/tests/__init__.py
odoo/addons/maintenance_plan_activity/tests/test_maintenance_plan_activity.py
odoo/addons/maintenance_plan_activity/views/maintenance_views.xml
odoo14_addon_maintenance_plan_activity-14.0.1.0.3.dist-info/METADATA
odoo14_addon_maintenance_plan_activity-14.0.1.0.3.dist-info/WHEEL
odoo14_addon_maintenance_plan_activity-14.0.1.0.3.dist-info/top_level.txt
odoo14_addon_maintenance_plan_activity-14.0.1.0.3.dist-info/RECORD
